MySQLPandas/__init__.py
MySQLPandas/core.py
MySQLPandas/lib/DataFrameClass.py
MySQLPandas/lib/ErrorClass.py
MySQLPandas/lib/__init__.py
MySQLPandas-0.0.19.dist-info/LICENSE
MySQLPandas-0.0.19.dist-info/METADATA
MySQLPandas-0.0.19.dist-info/WHEEL
MySQLPandas-0.0.19.dist-info/top_level.txt
MySQLPandas-0.0.19.dist-info/RECORD
