Metadata-Version: 2.1
Name: MySQLPandas
Version: 0.0.19
Summary: MySQLPandas: simple connector between MySQL(MariaDB) and Pandas
Home-page: https://github.com/Sota-Nakashima/MySQLPandas
Author: Sota-Nakashima
Author-email: souta.nakashima2001@gmail.com
License: GPLv2
Keywords: Python,Pandas,Database
Classifier: Development Status :: 4 - Beta
Classifier: License :: OSI Approved :: GNU General Public License v2 (GPLv2)
Classifier: Programming Language :: Python :: 3 :: Only
Classifier: Topic :: Database
Classifier: Topic :: Software Development :: Libraries :: Python Modules
License-File: LICENSE
Requires-Dist: mysql-connector-python (<=8.0.29)
Requires-Dist: pandas (<=1.5.3)
Requires-Dist: tqdm (<=4.65.0)
